{
  "updated": "2026-07-17T21:55:15.543Z",
  "items": [
    {
      "title": "Validade da prova digital: autenticidade, integridade e cadeia de custódia na jurisprudência do STJ",
      "link": "https://www.conjur.com.br/2026-jul-17/validade-da-prova-digital-autenticidade-integridade-e-cadeia-de-custodia-na-jurisprudencia-do-stj/",
      "source": "ConJur",
      "date": "2026-07-17T21:25:00.000Z"
    },
    {
      "title": "Sócia do Sanmahe Advogados modera painel sobre benefícios fiscais em workshop da Apet",
      "link": "https://www.conjur.com.br/2026-jul-17/socia-do-sanmahe-advogados-modera-painel-sobre-beneficios-fiscais-em-workshop-da-apet/",
      "source": "ConJur",
      "date": "2026-07-17T21:00:19.000Z"
    },
    {
      "title": "CNPJ ativo não basta para provar que empresa continua em operação",
      "link": "https://www.conjur.com.br/2026-jul-17/cnpj-ativo-nao-basta-para-provar-que-empresa-continua-em-operacao/",
      "source": "ConJur",
      "date": "2026-07-17T20:53:11.000Z"
    },
    {
      "title": "Mulher denuncia clínica após ter cabelo raspado em exame toxicológico para CNH",
      "link": "https://www.direitonews.com.br/2026/07/mulher-denuncia-clinica-apos-ter-cabelo-raspado-exame-toxicologico-cnh.html",
      "source": "Direito News",
      "date": "2026-07-17T20:41:47.000Z"
    },
    {
      "title": "Arrematante sem imissão na posse bate à porta do condomínio: e agora, síndico?",
      "link": "https://www.conjur.com.br/2026-jul-17/arrematante-sem-imissao-na-posse-bate-a-porta-do-condominio-e-agora-sindico/",
      "source": "ConJur",
      "date": "2026-07-17T20:21:10.000Z"
    },
    {
      "title": "Erros gerados por inteligência artificial preocupam advogados e levam OAB a criar ferramenta de verificação",
      "link": "https://www.direitonews.com.br/2026/07/erros-gerados-inteligencia-artificial-preocupam-advogados-levam-oab-criar-ferramenta-verificacao.html",
      "source": "Direito News",
      "date": "2026-07-17T20:16:51.000Z"
    },
    {
      "title": "Prefeitura do Rio lança guia sobre o uso ético da IA no serviço público",
      "link": "https://www.conjur.com.br/2026-jul-17/prefeitura-do-rio-lanca-guia-sobre-o-uso-etico-da-ia-no-servico-publico/",
      "source": "ConJur",
      "date": "2026-07-17T20:00:17.000Z"
    },
    {
      "title": "Tarifa adicional de esgoto não pode ser cobrada sem prova de dano",
      "link": "https://www.conjur.com.br/2026-jul-17/tarifa-de-carga-poluidora-nao-pode-ser-cobrada-sem-prova-do-dano/",
      "source": "ConJur",
      "date": "2026-07-17T19:51:43.000Z"
    },
    {
      "title": "Assinatura basta? Consentimento, boa-fé e validade do aval nas relações bancárias",
      "link": "https://www.conjur.com.br/2026-jul-17/assinatura-basta-consentimento-boa-fe-e-validade-do-aval-nas-relacoes-bancarias/",
      "source": "ConJur",
      "date": "2026-07-17T19:24:38.000Z"
    }
  ]
}
