{
  "updated": "2026-07-14T21:58:46.890Z",
  "items": [
    {
      "title": "Impugnação retardatária pelo devedor e a primazia da realidade substantiva do crédito",
      "link": "https://www.conjur.com.br/2026-jul-14/impugnacao-retardataria-pelo-devedor-e-a-primazia-da-realidade-substantiva-do-credito/",
      "source": "ConJur",
      "date": "2026-07-14T21:25:42.000Z"
    },
    {
      "title": "STF já decidiu mais de 400 vezes pela competência da Justiça comum em casos de pejotização",
      "link": "https://www.conjur.com.br/2026-jul-14/stf-ja-decidiu-mais-de-400-vezes-pela-competencia-da-justica-comum-em-casos-de-pejotizacao/",
      "source": "ConJur",
      "date": "2026-07-14T20:52:26.000Z"
    },
    {
      "title": "Gusttavo Lima surpreende ao falar do presidente Lula: “Estamos aqui para apoiar”. VÍDEO",
      "link": "https://www.direitonews.com.br/2026/07/gusttavo-lima-surpreende-falar-presidente-lula-estamos-aqui-apoiar-video.html",
      "source": "Direito News",
      "date": "2026-07-14T20:51:37.000Z"
    },
    {
      "title": "OAB pede que Alexandre de Moraes libere visitas de Flávio a Bolsonaro como advogado",
      "link": "https://www.direitonews.com.br/2026/07/oab-pede-alexandre-moraes-libere-visitas-flavio-bolsonaro-como-advogado.html",
      "source": "Direito News",
      "date": "2026-07-14T20:36:49.000Z"
    },
    {
      "title": "Negociação coletiva no serviço público volta à pauta no Congresso",
      "link": "https://www.conjur.com.br/2026-jul-14/os-caminhos-da-regulamentacao-da-negociacao-coletiva-no-servico-publico-no-brasil-breves-comentarios-sobre-o-projeto-de-lei-no-1-893-2026/",
      "source": "ConJur",
      "date": "2026-07-14T20:24:24.000Z"
    },
    {
      "title": "Hospital filantrópico deve permitir fiscalização de serviços do SUS",
      "link": "https://www.conjur.com.br/2026-jul-14/hospital-filantropico-deve-permitir-fiscalizacao-de-servicos-do-sus/",
      "source": "ConJur",
      "date": "2026-07-14T19:51:56.000Z"
    },
    {
      "title": "Deepfakes: passado, presente e futuro nas eleições brasileiras",
      "link": "https://www.conjur.com.br/2026-jul-14/deepfakes-passado-presente-e-futuro-nas-eleicoes-brasileiras/",
      "source": "ConJur",
      "date": "2026-07-14T19:21:54.000Z"
    },
    {
      "title": "Abuso de confiança: venda de imóvel é declarada nula após advogada induzir idosos a erro",
      "link": "https://www.direitonews.com.br/2026/07/abuso-confianca-venda-imovel-declarada-nula-apos-advogada-induzir-idosos-erro.html",
      "source": "Direito News",
      "date": "2026-07-14T19:13:42.000Z"
    },
    {
      "title": "Dino reforça que emendas parlamentares não podem ser controladas por terceiros",
      "link": "https://www.conjur.com.br/2026-jul-14/dino-reforca-que-emendas-parlamentares-nao-podem-ser-controladas-por-terceiros/",
      "source": "ConJur",
      "date": "2026-07-14T18:51:28.000Z"
    }
  ]
}
